DrawPrint.py
DrawPrint-0.2.4.1.dist-info/LICENSE.txt
DrawPrint-0.2.4.1.dist-info/METADATA
DrawPrint-0.2.4.1.dist-info/WHEEL
DrawPrint-0.2.4.1.dist-info/top_level.txt
DrawPrint-0.2.4.1.dist-info/RECORD
