Metadata-Version: 2.2
Name: DrawPrint
Version: 0.2.4.1
Summary: DrawPrint
Author: huang yi yi
Author-email: 363766687@qq.com
Requires-Python: >=3.6
License-File: LICENSE.txt
Requires-Dist: pyfiglet>=0.8.post1
Requires-Dist: pygame>=2.6.0.post1
Requires-Dist: pyecharts>=2.0.6.post1
Requires-Dist: requests>=2.32.2.post1
Requires-Dist: pypiwin32>=219.post1
Requires-Dist: cutecharts>=1.1.9
Requires-Dist: pywebio>=1.8.2
Dynamic: author
Dynamic: author-email
Dynamic: description
Dynamic: requires-dist
Dynamic: requires-python
Dynamic: summary
